{
    "name": "jmb-c8000v",
    "region": "westeurope",
    "rg": "jmb-rg-vnet1",
    "virtual_network": "jmb-vnet1",
    "subnet_transport": "jmb-subnet-transport",
    "subnet_service": "jmb-subnet-service",
    "image_id": "17_07_01a-byol",
    "instance_type": "Standard_DS1_v2",
    "ntp_server": "time.nist.gov",
    "organization": "ciscotme",
    "site_id": "122",
    "system_ip": "10.0.0.100",
    "vbond_ip": "10.10.10.10",
    "uuid": "C8K-ACD21A8B-1AF7-E531-4AFC-7A9C0BFFAEBF",
    "token": "654ccd54050545ae89ada94fb44f8561",
    "username": "cisco",
    "password": "Cisco123#"
}